seqclupv/SeqClu.py
seqclupv/SeqCluBaselineOffline.py
seqclupv/SeqCluBaselineOnline.py
seqclupv/__init__.py
seqclupv/__main__.py
seqclupv/data/__init__.py
seqclupv/data/GesturePebbleZ1/GesturePebbleZ1_TEST.ts
seqclupv/data/GesturePebbleZ1/GesturePebbleZ1_TRAIN.ts
seqclupv/data/PLAID/PLAID_TEST.ts
seqclupv/data/PLAID/PLAID_TRAIN.ts
seqclupv/data/handwriting/UJIpenchars-w01
seqclupv/data/handwriting/UJIpenchars-w02
seqclupv/data/handwriting/UJIpenchars-w03
seqclupv/data/handwriting/UJIpenchars-w04
seqclupv/data/handwriting/UJIpenchars-w05
seqclupv/data/handwriting/UJIpenchars-w06
seqclupv/data/handwriting/UJIpenchars-w07
seqclupv/data/handwriting/UJIpenchars-w08
seqclupv/data/handwriting/UJIpenchars-w09
seqclupv/data/handwriting/UJIpenchars-w10
seqclupv/data/handwriting/UJIpenchars-w11
seqclupv/data/handwriting/desktop.ini
seqclupv/data/handwriting/test
seqclupv/library/__init__.py
seqclupv/library/data_generator/__init__.py
seqclupv/library/data_generator/handwritten_character_generator.py
seqclupv/library/data_generator/pebble_generator.py
seqclupv/library/data_generator/plaid_generator.py
seqclupv/library/data_generator/sine_curve_generator.py
seqclupv/library/data_generator/time_series_classification_base.py
seqclupv/library/data_source/__init__.py
seqclupv/library/data_source/fake_data_source.py
seqclupv/library/distance/__init__.py
seqclupv/library/distance/dynamic_time_warping.py
seqclupv/library/evaluation/__init__.py
seqclupv/library/evaluation/basic_baseline_prototypes.py
seqclupv/library/evaluation/basic_evaluator.py
seqclupv/library/heuristics/__init__.py
seqclupv/library/heuristics/linear_prototype_value.py
seqclupv/library/interfaces/__init__.py
seqclupv/library/interfaces/baseline_prototypes.py
seqclupv/library/interfaces/candidate_store.py
seqclupv/library/interfaces/data_generator.py
seqclupv/library/interfaces/data_source.py
seqclupv/library/interfaces/distance_measure.py
seqclupv/library/interfaces/evaluator.py
seqclupv-1.0.3.dist-info/LICENSE
seqclupv-1.0.3.dist-info/METADATA
seqclupv-1.0.3.dist-info/WHEEL
seqclupv-1.0.3.dist-info/top_level.txt
seqclupv-1.0.3.dist-info/RECORD
