Metadata-Version: 2.1
Name: seqclupv
Version: 1.0.3
Summary: An extension of the original 'SeqClu' algorithm that is characterized by voting for cluster prototypes.
Home-page: https://github.com/rtewierik/seqclupv
Author: R. E. C. te Wierik
Author-email: r.e.c.tewierik@student.tudelft.nl
License: UNKNOWN
Project-URL: Bug Tracker, https://github.com/rtewierik/seqclupv/issues
Platform: UNKNOWN
Classifier: Programming Language :: Python :: 3
Classifier: License :: OSI Approved :: MIT License
Classifier: Operating System :: OS Independent
Requires-Python: >=3.9
License-File: LICENSE
Requires-Dist: fastdtw (>=0.3.4)
Requires-Dist: numpy (>=1.20.3)
Requires-Dist: seaborn (>=0.11.1)
Requires-Dist: matplotlib (>=3.4.2)
Requires-Dist: sklearn (>=0.0)
Requires-Dist: scipy (>=1.6.3)
Requires-Dist: pandas (>=1.2.4)
Requires-Dist: ipython (>=7.24.1)
Requires-Dist: xxhash (>=2.0.2)
Requires-Dist: psutil (>=5.8.0)
Requires-Dist: sktime (>=0.6.1)
